transidate/__init__.py
transidate/cli.py
transidate/console.py
transidate/datasets.py
transidate/default.ini
transidate/exceptions.py
transidate/outputs.py
transidate/typing.py
transidate/validators.py
transidate/violations.py
transidate-0.4.0.dist-info/WHEEL
transidate-0.4.0.dist-info/METADATA
transidate-0.4.0.dist-info/entry_points.txt
transidate-0.4.0.dist-info/RECORD
