Metadata-Version: 2.1
Name: transidate
Version: 0.4.0
Summary: Commandline tool for XML transit data validation.
Author: Ciaran McCormick
Author-email: ciaran@ciaranmccormick.com
Requires-Python: >=3.7,<4.0
Classifier: Programming Language :: Python :: 3
Classifier: Programming Language :: Python :: 3.7
Classifier: Programming Language :: Python :: 3.8
Classifier: Programming Language :: Python :: 3.9
Classifier: Programming Language :: Python :: 3.10
Classifier: Programming Language :: Python :: 3.11
Requires-Dist: click (>=8.0.0)
Requires-Dist: cryptography (>=3.3.0)
Requires-Dist: lxml (>=4.6.0)
Requires-Dist: prettytable (>=2.0.0)
Requires-Dist: pydantic (>=1.8.0)
Requires-Dist: requests (>=2.24.0)
Requires-Dist: rich (>=9.12.0)
